geckoprofiler_controller
tests
