Metadata-Version: 1.0
Name: geckoprofiler-controller
Version: 0.0.4
Summary: Control the Gecko Profiler by Python and Web Socket
Home-page: https://github.com/askeing/geckoprofiler_controller
Author: Askeing Yen
Author-email: askeing@gmail.com
License: MPL
Keywords: mozilla firefox gecko profiler utilities
Platform: UNKNOWN
